Workbook
Name _311: '[1]Brasil Volumes Cecafe Calendar'!#REF!
Name ANU: #REF!
Name COMPAR: #REF!
Name LINHA: '[1]Brasil Volumes Cecafe Calendar'!#REF!
Name mts: '[2]ENTER DATA HERE'!$1:$1048576
Name SAFRA: #REF!
Name VERDE: '[1]Brasil Volumes Cecafe Calendar'!#REF!

Sheet Coffee SnD ETG
A1: Brazil Combo | B1: =B5+B21 -> 57.3 | C1: =C5+C21 -> 50.6 | D1: =D5+D21 -> 67 | E1: =E5+E21 -> 60 | F1: =F5+F21 -> 73 | G1: =G5+G21 -> 58 | H1: =H5+H21 -> 60 | I1: =I5+I21 -> 66 | ... M1: =M5+M21 -> 66
A2: Jul- Jun | B2: SnD ETG
A3: Arabica | AE3: 2006/07 | AF3: 2007/08 | AG3: 2008/09 | AH3: 2009/10 | AI3: 2010/11 | AJ3: 2011/12 | AK3: 2012/13 | AL3: 2013/14 | AM3: 2014/15 | AN3: 2015/16 | AO3: 2016/17 | AP3: 2017/18 | AQ3: 2018/19 | AR3: 2019/20 | AS3: 2020/21 | AT3: 2021/22 | AU3: 2022/23 | AV3: 2023/24
B4: 2016/17 | C4: 2017/18 | D4: 2018/19 | E4: 2019/20 | F4: 2020/21 | G4: 2021/22 | H4: 2022/23* | I4: 2023/24* | J4: 2024/25* | K4: 2025/26* | L4: 2026/27* | M4: 2027/28* | AD4: Arabica | AE4: 0.46 | AF4: 0.35 | AG4: 0.39 | AH4: 0.26 | AI4: 0.305 | AJ4: 0.31 | AK4: 0.39 | AL4: 0.385 | AM4: 0.31 | AN4: 0.25 | AO4: 0.28 | AP4: 0.26 | AQ4: 0.295 | AR4: 0.26 | AS4: 0.31 | AT4: 0.275 | AU4: 0.31 | AV4: 0.395 | AW4: =AVERAGE(AE4:AV4) -> 0.32194444
A5: Brazil | B5: 45.7 | C5: 37.3 | D5: 48 | E5: 39 | F5: 53 | G5: 36 | H5: 37 | I5: 42 | J5: 43 | K5: 37 | L5: 50 | M5: 41 | AD5: S/U Change | AF5: =AF4-AE4 -> -0.11 | AG5: =AG4-AF4 -> 0.04 | AH5: =AH4-AG4 -> -0.13 | AI5: =AI4-AH4 -> 0.045 | AJ5: =AJ4-AI4 -> 0.005 | AK5: =AK4-AJ4 -> 0.08 | AL5: =AL4-AK4 -> -0.005 | AM5: =AM4-AL4 -> -0.075 | ... AV5: =AV4-AU4 -> 0.085
A6: Colombia | B6: 14.6 | C6: 13.4 | D6: 13.9 | E6: 13.8 | F6: 13.2 | G6: 11.7 | H6: 10.5 | I6: 12 | J6: 14.5 | K6: 12.5 | L6: 13.5 | M6: 14 | AD6: Robusta | AE6: 0.2 | AF6: 0.21 | AG6: 0.26 | AH6: 0.225 | AI6: 0.255 | AJ6: 0.19 | AK6: 0.2 | AL6: 0.23 | AM6: 0.265 | AN6: 0.245 | AO6: 0.245 | AP6: 0.2 | AQ6: 0.21 | AR6: 0.205 | AS6: 0.21 | AT6: 0.175 | AU6: 0.145 | AV6: 0.145 | AW6: =AVERAGE(AE6:AV6) -> 0.21194444
A7: Honduras | B7: 7.8 | C7: 7.8 | D7: 7.4 | E7: 6.1 | F7: 6.5 | G7: 4.9 | H7: 5.5 | I7: 4.9 | J7: 5.3 | K7: 6 | L7: 5.6 | M7: 5.6 | AD7: S/U Change | AF7: =AF6-AE6 -> 0.01 | AG7: =AG6-AF6 -> 0.05 | AH7: =AH6-AG6 -> -0.035 | AI7: =AI6-AH6 -> 0.03 | AJ7: =AJ6-AI6 -> -0.065 | AK7: =AK6-AJ6 -> 0.01 | AL7: =AL6-AK6 -> 0.03 | AM7: =AM6-AL6 -> 0.035 | ... AV7: =AV6-AU6 -> 0
A8: Super 5 | B8: 12 | C8: 12.3 | D8: 12.1 | E8: 11.6 | F8: 12 | G8: 11.7 | H8: 12.5 | I8: 13 | J8: 13.5 | K8: 13.8 | L8: 13.8 | M8: 14 | AD8: A-R | AE8: =AE4-AE6 -> 0.26 | AF8: =AF4-AF6 -> 0.14 | AG8: =AG4-AG6 -> 0.13 | AH8: =AH4-AH6 -> 0.035 | AI8: =AI4-AI6 -> 0.05 | AJ8: =AJ4-AJ6 -> 0.12 | AK8: =AK4-AK6 -> 0.19 | AL8: =AL4-AL6 -> 0.155 | ... AV8: =AV4-AV6 -> 0.25 | AW8: =AVERAGE(AE8:AV8) -> 0.11
A9: Ethiopia | B9: 5.9 | C9: 5.8 | D9: 6.4 | E9: 6.5 | F9: 7.1 | G9: 7.2 | H9: 7.4 | I9: 7.5 | J9: 7.5 | K9: 8 | L9: 7.2 | M9: 7.2 | AD9: ARB end Jun | AF9: 46.47 | AG9: 59.34 | AH9: 87.33 | AI9: 152.3 | AJ9: 73.9 | AK9: 40.6 | AL9: 83.6 | AM9: 51.48 | AN9: 67.7 | AO9: 28.2 | AP9: 38.4 | AQ9: 43.6 | AR9: 47.2 | AS9: 82.4 | AT9: 137.9 | AW9: =AVERAGE(AF9:AV9) -> 69.361333
A10: Peru | B10: 4.1 | C10: 4.3 | D10: 4.4 | E10: 3.8 | F10: 4 | G10: 4.2 | H10: 3.6 | I10: 4.5 | J10: 4 | K10: 4 | L10: 4 | M10: 4 | AD10: Arb Change | AG10: =AG9-AF9 -> 12.87 | AH10: =AH9-AG9 -> 27.99 | AI10: =AI9-AH9 -> 64.97 | AJ10: =AJ9-AI9 -> -78.4 | AK10: =AK9-AJ9 -> -33.3 | AL10: =AL9-AK9 -> 43 | AM10: =AM9-AL9 -> -32.12 | AN10: =AN9-AM9 -> 16.22 | ... AT10: =AT9-AS9 -> 55.5
A11: Others | B11: 10.3 | C11: 10.9 | D11: 10.7 | E11: 9.6 | F11: 8.7 | G11: 9.4 | H11: 9.4 | I11: 9.4 | J11: 9.4 | K11: 11 | L11: 9.4 | M11: 9.4 | AD11: ARB avg Jul-Jun | AF11: 37 | AG11: 45 | AH11: 73 | AI11: 132 | AJ11: 125 | AK11: 61 | AL11: 59.8 | AM11: 79.9 | AN11: 54 | AO11: 53.1 | AP11: 42.3 | AQ11: 35 | AR11: 49.8 | AS11: 63.1 | AT11: 118.8 | AW11: =AVERAGE(AF11:AV11) -> 68.586667
A12: Production | B12: =SUM(B5:B11) -> 100.4 | C12: =SUM(C5:C11) -> 91.8 | D12: =SUM(D5:D11) -> 102.9 | E12: =SUM(E5:E11) -> 90.4 | F12: =SUM(F5:F11) -> 104.5 | G12: =SUM(G5:G11) -> 85.1 | H12: =SUM(H5:H11) -> 85.9 | I12: =SUM(I5:I11) -> 93.3 | ... L12: =SUM(L5:L11) -> 103.5 | M12: 98.4 | AD12: Arb Change | AG12: =AG11-AF11 -> 8 | AH12: =AH11-AG11 -> 28 | AI12: =AI11-AH11 -> 59 | AJ12: =AJ11-AI11 -> -7 | AK12: =AK11-AJ11 -> -64 | AL12: =AL11-AK11 -> -1.2 | AM12: =AM11-AL11 -> 20.1 | AN12: =AN11-AM11 -> -25.9 | ... AT12: =AT11-AS11 -> 55.7
A13: Consumption | B13: 94.2 | C13: 93.5 | D13: 97.9 | E13: 94.6 | F13: 96 | G13: 91.4 | H13: 89 | I13: 92.5 | J13: 99 | K13: 98 | L13: 96 | M13: 97 | AD13: Arabica/Robusta S/U | AE13: =AE4/AE6 -> 2.3 | AF13: =AF4/AF6 -> 1.6666667 | AG13: =AG4/AG6 -> 1.5 | AH13: =AH4/AH6 -> 1.1555556 | AI13: =AI4/AI6 -> 1.1960784 | AJ13: =AJ4/AJ6 -> 1.6315789 | AK13: =AK4/AK6 -> 1.95 | AL13: =AL4/AL6 -> 1.673913 | ... AW13: =AW4/AW6 -> 1.5190039
A14: Consumption % | C14: =C13/B13-1 -> -0.0074309979 | D14: =D13/C13-1 -> 0.047058824 | E14: =E13/D13-1 -> -0.033707865 | F14: =F13/E13-1 -> 0.014799154 | G14: =G13/F13-1 -> -0.047916667 | H14: =H13/G13-1 -> -0.026258206 | I14: =I13/H13-1 -> 0.039325843 | J14: =J13/I13-1 -> 0.07027027 | ... M14: =M13/L13-1 -> 0.010416667 | AD14: Relative S/U change | AF14: =AF5-AF7 -> -0.12 | AG14: =AG5-AG7 -> -0.01 | AH14: =AH5-AH7 -> -0.095 | AI14: =AI5-AI7 -> 0.015 | AJ14: =AJ5-AJ7 -> 0.07 | AK14: =AK5-AK7 -> 0.07 | AL14: =AL5-AL7 -> -0.035 | AM14: =AM5-AM7 -> -0.11 | ... AV14: =AV5-AV7 -> 0.085
A15: Balance | B15: =B12-B13 -> 6.2 | C15: =C12-C13 -> -1.7 | D15: =D12-D13 -> 5 | E15: =E12-E13 -> -4.2 | F15: =F12-F13 -> 8.5 | G15: =G12-G13 -> -6.3 | H15: =H12-H13 -> -3.1 | I15: =I12-I13 -> 0.8 | ... M15: =M12-M13 -> 1.4 | AD15: Arbica SnD | AO15: 5.6 | AP15: -1.7 | AQ15: 5 | AR15: -4.2 | AS15: 8.2 | AT15: -4.9 | AU15: 3.2 | AV15: 8.7
A16: End Season Stock | B16: 26.4 | C16: =B16+C15 -> 24.7 | D16: =C16+D15 -> 29.7 | E16: =D16+E15 -> 25.5 | F16: =E16+F15 -> 34 | G16: =F16+G15 -> 27.7 | H16: =G16+H15 -> 24.6 | I16: =H16+I15 -> 25.4 | J16: =I16+J15 -> 23.6 | ... M16: =L16+M15 -> 26.8 | AD16: Robusta SnD | AO16: -1.9 | AP16: -1.3 | AQ16: 1.5 | AR16: 0.7 | AS16: 3.7 | AT16: -1.5 | AU16: -2.1 | AV16: -0.1
A17: S/U | B17: =B16/B13 -> 0.28025478 | C17: =C16/C13 -> 0.26417112 | D17: =D16/D13 -> 0.30337079 | E17: =E16/E13 -> 0.26955603 | F17: =F16/F13 -> 0.35416667 | G17: =G16/G13 -> 0.30306346 | H17: =H16/H13 -> 0.27640449 | I17: =I16/I13 -> 0.27459459 | ... M17: =M16/M13 -> 0.27628866
A18: Robusta
B19: 2016/17 | C19: 2017/18 | D19: 2018/19 | E19: 2019/20 | F19: 2020/21 | G19: 2021/22 | H19: 2022/23 | I19: 2023/24 | J19: 2024/25* | K19: 2025/26* | L19: 2026/27* | M19: 2027/28* | AN19: Everyone saying there is no selling from Brazil
A20: Vietnam | B20: 23.1 | C20: 29 | D20: 27.9 | E20: 27.7 | F20: 26.5 | G20: 29.1 | H20: 28.5 | I20: 27.5 | J20: 27 | K20: 30 | L20: 29 | M20: 29.5 | AN20: Despite that 23/24 is sold for 12% starting Sep 21, pretty linear since they started
A21: Brazil | B21: 11.6 | C21: 13.3 | D21: 19 | E21: 21 | F21: 20 | G21: 22 | H21: 23 | I21: 24 | J21: 22 | K21: 26 | L21: 24.6 | M21: 25 | AN21: For comparison 2 previous seasons were 18% and 22%
A22: Indonesia | B22: 12.1 | C22: 9 | D22: 9.6 | E22: 10.8 | F22: 12.1 | G22: 12.1 | H22: 10.5 | I22: 8 | J22: 10.8 | K22: 10.8 | L22: 10.5 | M22: 11 | AN22: It's true 22/23 found a clip of selling in the April to Nov period, into and post frost
A23: India | B23: 5.2 | C23: 5 | D23: 4.8 | E23: 4.3 | F23: 4.9 | G23: 5.5 | H23: 4.9 | I23: 5.5 | J23: 5 | K23: 5 | L23: 5.5 | M23: 5.5
A24: Uganda | B24: 4.1 | C24: 3.7 | D24: 4 | E24: 4.9 | F24: 6.3 | G24: 5.5 | H24: 5.5 | I24: 6.5 | J24: 7 | K24: 7 | L24: 7 | M24: 7
A25: Cote d'Ivoire | B25: 1.4 | C25: 2.1 | D25: 2.1 | E25: 1.9 | F25: 1.4 | G25: 1.5 | H25: 0.9 | I25: 1.8 | J25: 1.5 | K25: 1.5 | L25: 1.5 | M25: 1.5
A26: Others | B26: 5.3 | C26: 5.1 | D26: 5.7 | E26: 5.1 | F26: 4.9 | G26: 4.7 | H26: 4.6 | I26: 4.8 | J26: 4.9 | K26: 5 | L26: 5 | M26: 5
A27: Production | B27: =SUM(B20:B26) -> 62.8 | C27: =SUM(C20:C26) -> 67.2 | D27: =SUM(D20:D26) -> 73.1 | E27: =SUM(E20:E26) -> 75.7 | F27: =SUM(F20:F26) -> 76.1 | G27: =SUM(G20:G26) -> 80.4 | H27: =SUM(H20:H26) -> 77.9 | I27: =SUM(I20:I26) -> 78.1 | ... L27: =SUM(L20:L26) -> 83.1 | M27: 84.5
A28: Consumption | B28: 64.6 | C28: 68.6 | D28: 71.6 | E28: 74 | F28: 72 | G28: 81.3 | H28: 83.1 | I28: 82 | J28: 76 | K28: 78 | L28: 81 | M28: 81
A29: Consumption % | C29: =C28/B28-1 -> 0.061919505 | D29: =D28/C28-1 -> 0.043731778 | E29: =E28/D28-1 -> 0.033519553 | F29: =F28/E28-1 -> -0.027027027 | G29: =G28/F28-1 -> 0.12916667 | H29: =H28/G28-1 -> 0.022140221 | I29: =I28/H28-1 -> -0.013237064 | J29: =J28/I28-1 -> -0.073170732 | ... L29: =L28/K28-1 -> 0.038461538 | M29: s
A30: Balance | B30: =B27-B28 -> -1.8 | C30: =C27-C28 -> -1.4 | D30: =D27-D28 -> 1.5 | E30: =E27-E28 -> 1.7 | F30: =F27-F28 -> 4.1 | G30: =G27-G28 -> -0.9 | H30: =H27-H28 -> -5.2 | I30: =I27-I28 -> -3.9 | ... M30: =M27-M28 -> 3.5
A31: End Season Stock | B31: 15.9 | C31: =B31+C30 -> 14.5 | D31: =C31+D30 -> 16 | E31: =D31+E30 -> 17.7 | F31: =E31+F30 -> 21.8 | G31: =F31+G30 -> 20.9 | H31: =G31+H30 -> 15.7 | I31: =H31+I30 -> 11.8 | J31: =I31+J30 -> 14 | ... M31: =L31+M30 -> 26.9
A32: S/U | B32: =B31/B28 -> 0.24613003 | C32: =C31/C28 -> 0.21137026 | D32: =D31/D28 -> 0.22346369 | E32: =E31/E28 -> 0.23918919 | F32: =F31/F28 -> 0.30277778 | G32: =G31/G28 -> 0.25707257 | H32: =H31/H28 -> 0.188929 | I32: =I31/I28 -> 0.14390244 | ... M32: =M31/M28 -> 0.33209877
A33: Robusta demand share | B33: =B28/B37 -> 0.40680101 | C33: =C28/C37 -> 0.42319556 | D33: =D28/D37 -> 0.42241888 | E33: =E28/E37 -> 0.43890866 | F33: =F28/F37 -> 0.42857143 | G33: =G28/G37 -> 0.47075854 | H33: =H28/H37 -> 0.4828588 | I33: =I28/I37 -> 0.46991404 | ... L33: =L28/L37 -> 0.45762712 | M33: 0.4640884
B34: Global
B35: 2016/17 | C35: 2017/18 | D35: 2018/19 | E35: 2019/20 | F35: 2020/21 | G35: 2021/22 | H35: 2022/23 | I35: 2023/24 | J35: 2024/25 | K35: 2025/26 | L35: 2026/27 | M35: 2027/28
A36: Production Global | B36: =B12+B27 -> 163.2 | C36: =C12+C27 -> 159 | D36: =D12+D27 -> 176 | E36: =E12+E27 -> 166.1 | F36: =F12+F27 -> 180.6 | G36: =G12+G27 -> 165.5 | H36: =H12+H27 -> 163.8 | I36: =I12+I27 -> 171.4 | ... M36: =M12+M27 -> 182.9
A37: Consumption Global | B37: =B13+B28 -> 158.8 | C37: =C13+C28 -> 162.1 | D37: =D13+D28 -> 169.5 | E37: =E13+E28 -> 168.6 | F37: =F13+F28 -> 168 | G37: =G13+G28 -> 172.7 | H37: =H13+H28 -> 172.1 | I37: =I13+I28 -> 174.5 | ... M37: =M13+M28 -> 178
A38: Global Balance | B38: =B36-B37 -> 4.4 | C38: =C36-C37 -> -3.1 | D38: =D36-D37 -> 6.5 | E38: =E36-E37 -> -2.5 | F38: =F36-F37 -> 12.6 | G38: =G36-G37 -> -7.2 | H38: =H36-H37 -> -8.3 | I38: =I36-I37 -> -3.1 | ... M38: =M36-M37 -> 4.9
A39: 2 year cycle | B39: 2016/18 | D39: 2018/20 | F39: 2020/22 | H39: 2022/24 | J39: 2024/26 | L39: 2026/28
A40: Global Balance | B40: =B38+C38 -> 1.3 | D40: =D38+E38 -> 4 | F40: =F38+G38 -> 5.4 | H40: =H38+I38 -> -11.4 | J40: =J38+K38 -> 2 | L40: =L38+M38 -> 14.5
A41: Global demand chg | C41: =C37/B37-1 -> 0.020780856 | D41: =D37/C37-1 -> 0.045650833 | E41: =E37/D37-1 -> -0.0053097345 | F41: =F37/E37-1 -> -0.0035587189 | G41: =G37/F37-1 -> 0.02797619 | H41: =H37/G37-1 -> -0.0034742328 | I41: =I37/H37-1 -> 0.013945381 | J41: =J37/I37-1 -> 0.0028653295 | ... M41: =M37/L37-1 -> 0.0056497175
A42: Combined End Season Stock | B42: =B16+B31 -> 42.3 | C42: =C16+C31 -> 39.2 | D42: =D16+D31 -> 45.7 | E42: =E16+E31 -> 43.2 | F42: =F16+F31 -> 55.8 | G42: =G16+G31 -> 48.6 | H42: =H16+H31 -> 40.3 | I42: =I16+I31 -> 37.2 | ... M42: =M16+M31 -> 53.7
A43: Combined S/U | B43: =(B16+B31)/(B13+B28) -> 0.2663728 | C43: =(C16+C31)/(C13+C28) -> 0.24182603 | D43: =(D16+D31)/(D13+D28) -> 0.26961652 | E43: =(E16+E31)/(E13+E28) -> 0.25622776 | F43: =(F16+F31)/(F13+F28) -> 0.33214286 | G43: =(G16+G31)/(G13+G28) -> 0.28141285 | H43: =(H16+H31)/(H13+H28) -> 0.23416618 | I43: =(I16+I31)/(I13+I28) -> 0.21318052 | ... M43: =(M16+M31)/(M13+M28) -> 0.30168539
B79: 2016/17 | C79: 2017/18 | D79: 2018/19 | E79: 2019/20 | F79: 2020/21 | G79: 2021/22 | H79: 2022/23 | I79: 2023/24 | J79: 2024/25 | K79: 2025/26 | L79: 2026/27 | M79: 2027/28
B80: 2016/18 | D80: 2018/20 | F80: 2020/22 | H80: 2022/24 | J80: 2024/26 | L80: 2026/28
A81: Arabica | B81: =B83+C83 -> 4.5 | D81: =D83+E83 -> 0.8 | F81: =F83+G83 -> 2.2 | H81: =H83+I83 -> -2.3 | J81: =J83+K83 -> -7.5 | L81: =L83+M83 -> 8.9
A82: Robusta | B82: =B84+C84 -> -3.2 | D82: =D84+E84 -> 3.2 | F82: =F84+G84 -> 3.2 | H82: =H84+I84 -> -9.1 | J82: =J84+K84 -> 9.5 | L82: =L84+M84 -> 5.6
A83: Arabica | B83: =B15 -> 6.2 | C83: =C15 -> -1.7 | D83: =D15 -> 5 | E83: =E15 -> -4.2 | F83: =F15 -> 8.5 | G83: =G15 -> -6.3 | H83: =H15 -> -3.1 | I83: =I15 -> 0.8 | ... M83: =M15 -> 1.4
A84: Robusta | B84: =B30 -> -1.8 | C84: =C30 -> -1.4 | D84: =D30 -> 1.5 | E84: =E30 -> 1.7 | F84: =F30 -> 4.1 | G84: =G30 -> -0.9 | H84: =H30 -> -5.2 | I84: =I30 -> -3.9 | ... M84: =M30 -> 3.5
O107: 1. Overall tight coffee complex?
O108: 2. Diverging coffee prices?
O109: 3. Robusta strength or Arabica weakness

Sheet Timestamp
A1: =NOW() -> 46314.64

Sheet Brazil internal SnD
A1: Jul-Jun | B1: Brazil Internal SnD (mn Bags)
A2: Arabica | B2: 14/15 | C2: 15/16 | D2: 16/17 | E2: 17/18 | F2: 18/19 | G2: 19/20 | H2: 20/21 | I2: 21/22 | J2: 22/23 | K2: 23/24 | L2: 24/25* | M2: 25/26* | N2: 26/27* | O2: 27/28 | P2: 28/29
A4: Production | B4: 32.1 | C4: 35.4 | D4: 45.7 | E4: 37.3 | F4: 48 | G4: 39 | H4: ='Coffee SnD ETG'!F5 -> 53 | I4: ='Coffee SnD ETG'!G5 -> 36 | J4: ='Coffee SnD ETG'!H5 -> 37 | K4: ='Coffee SnD ETG'!I5 -> 42 | L4: ='Coffee SnD ETG'!J5 -> 43 | M4: ='Coffee SnD ETG'!K5 -> 37 | N4: ='Coffee SnD ETG'!L5 -> 50 | O4: ='Coffee SnD ETG'!M5 -> 41
A5: Exports | B5: 28.5 | C5: 29.5 | D5: 29 | E5: 26.2 | F5: 33.7 | G5: 31.7 | H5: 36.9 | I5: 33 | J5: 30.3 | K5: 35.5 | L5: 34.8 | M5: 32 | N5: 32 | O5: 32
A6: Consumption | B6: 9.1 | C6: 9.9 | D6: 14.2 | E6: 13 | F6: 11.2 | G6: 10.7 | H6: 11.7 | I6: =I7*I35 -> 7.08 | J6: =J7*J35 -> 7.11 | K6: =K7*K35 -> 10.8 | L6: =L7*L35 -> 9.6 | M6: =M7*M35 -> 5.75 | N6: =N7*N35 -> 8.05 | O6: =O7*O35 -> 10.8
A7: Demand as % of total | B7: =1-B24 -> 0.44 | C7: =1-C24 -> 0.47 | D7: =1-D24 -> 0.65 | E7: =1-E24 -> 0.57 | F7: =1-F24 -> 0.48 | G7: =1-G24 -> 0.46 | H7: =1-H24 -> 0.5 | I7: =1-I24 -> 0.3 | ... O7: =1-O24 -> 0.45
A8: Stock Change | B8: =B4-B5-B6 -> -5.5 | C8: =C4-C5-C6 -> -4 | D8: =D4-D5-D6 -> 2.5 | E8: =E4-E5-E6 -> -1.9 | F8: =F4-F5-F6 -> 3.1 | G8: =G4-G5-G6 -> -3.4 | H8: =H4-H5-H6 -> 4.4 | I8: =I4-I5-I6 -> -4.08 | ... O8: =O4-O5-O6 -> -1.8
A9: Closing Stock | B9: 15 | C9: =B9+C8 -> 11 | D9: =C9+D8 -> 13.5 | E9: =D9+E8 -> 11.6 | F9: =E9+F8 -> 14.7 | G9: =F9+G8 -> 11.3 | H9: =G9+H8 -> 15.7 | I9: =H9+I8 -> 11.62 | J9: =I9+J8 -> 11.21 | ... O9: =N9+O8 -> 12.91
A10: Exports % of Production | B10: =B5/B4 -> 0.88785047 | C10: =C5/C4 -> 0.83333333 | D10: =D5/D4 -> 0.6345733 | E10: =E5/E4 -> 0.70241287 | F10: =F5/F4 -> 0.70208333 | G10: =G5/G4 -> 0.81282051 | H10: =H5/H4 -> 0.69622642 | I10: =I5/I4 -> 0.91666667 | ... O10: =O5/O4 -> 0.7804878
A11: Consumption % of Production | B11: =B6/B4 -> 0.2834891 | C11: =C6/C4 -> 0.27966102 | D11: =D6/D4 -> 0.3107221 | E11: =E6/E4 -> 0.34852547 | F11: =F6/F4 -> 0.23333333 | G11: =G6/G4 -> 0.27435897 | H11: =H6/H4 -> 0.22075472 | I11: =I6/I4 -> 0.19666667 | ... O11: =O6/O4 -> 0.26341463
A12: Stock/Use Arabica | B12: =B9/B6 -> 1.6483516 | C12: =C9/C6 -> 1.1111111 | D12: =D9/D6 -> 0.95070423 | E12: =E9/E6 -> 0.89230769 | F12: =F9/F6 -> 1.3125 | G12: =G9/G6 -> 1.0560748 | H12: =H9/H6 -> 1.3418803 | I12: =I9/I6 -> 1.6412429 | ... O12: =O9/O6 -> 1.1953704
A13: All Coffee Stocks Brazil | B13: =B9+B26 -> 23 | C13: =C9+C26 -> 18.5 | D13: =D9+D26 -> 21.5 | E13: =E9+E26 -> 19.6 | F13: =F9+F26 -> 21.9 | G13: =G9+G26 -> 18.1 | H13: =H9+H26 -> 22.1 | I13: =I9+I26 -> 16.8 | ... O13: =O9+O26 -> 16.8
A14: Exports YoY | C14: =C5/B5-1 -> 0.035087719 | D14: =D5/C5-1 -> -0.016949153 | E14: =E5/D5-1 -> -0.096551724 | F14: =F5/E5-1 -> 0.28625954 | G14: =G5/F5-1 -> -0.059347181 | H14: =H5/G5-1 -> 0.16403785 | I14: =I5/H5-1 -> -0.10569106 | J14: =J5/I5-1 -> -0.081818182 | ... O14: =O5/N5-1 -> 0
A15: Arabica Consumption % | C15: =C6/B6-1 -> 0.087912088 | D15: =D6/C6-1 -> 0.43434343 | E15: =E6/D6-1 -> -0.084507042 | F15: =F6/E6-1 -> -0.13846154 | G15: =G6/F6-1 -> -0.044642857 | H15: =H6/G6-1 -> 0.093457944 | I15: =I6/H6-1 -> -0.39487179 | J15: =J6/I6-1 -> 0.0042372881 | ... O15: =O6/N6-1 -> 0.34161491
A17: Jul-Jun | B17: Brazil Internal SnD (mn Bags)
A18: Conillon | B18: 14/15 | C18: 15/16 | D18: 16/17 | E18: 17/18 | F18: 18/19 | G18: 19/20 | H18: 20/21 | I18: 21/22 | J18: 22/23 | K18: 23/24 | L18: 24/25* | M18: 25/26* | N18: 26/27* | O18: 27/28 | P18: 28/29
A20: Production | B20: 18.2 | C20: 16 | D20: ='Coffee SnD ETG'!B21 -> 11.6 | E20: ='Coffee SnD ETG'!C21 -> 13.3 | F20: ='Coffee SnD ETG'!D21 -> 19 | G20: ='Coffee SnD ETG'!E21 -> 21 | H20: ='Coffee SnD ETG'!F21 -> 20 | I20: ='Coffee SnD ETG'!G21 -> 22 | J20: ='Coffee SnD ETG'!H21 -> 23 | K20: ='Coffee SnD ETG'!I21 -> 24 | L20: 21.5 | M20: ='Coffee SnD ETG'!K21 -> 26 | N20: ='Coffee SnD ETG'!L21 -> 24.6 | O20: ='Coffee SnD ETG'!M21 -> 25
A21: Green Exports | B21: 4.5 | C21: 2.3 | D21: 0.3 | E21: 0.7 | F21: 3.6 | G21: 4.5 | H21: 4.7 | I21: 2.6 | J21: 1.5 | K21: 8.2 | L21: 6.6 | M21: 4.7 | N21: 4.6 | O21: 5
A22: Soluble Exports | B22: 2.8 | C22: 2.9 | D22: 3 | E22: 2.9 | F22: 4 | G22: 4.2 | H22: 4 | I22: 4.1 | J22: 3.8 | K22: 3.6 | L22: 4.2 | M22: 3.8 | N22: 3 | O22: 4
A23: Consumption | B23: 11.4 | C23: 11.3 | D23: 7.8 | E23: 9.7 | F23: 12.2 | G23: 12.7 | H23: 11.7 | I23: =I24*I35 -> 16.52 | J23: =J24*J35 -> 16.59 | K23: =K24*K35 -> 13.2 | L23: =L24*L35 -> 14.4 | M23: =M24*M35 -> 17.25 | N23: =N24*N35 -> 14.95 | O23: =O24*O35 -> 13.2
A24: Demand as % of total | B24: 0.56 | C24: 0.53 | D24: 0.35 | E24: 0.43 | F24: 0.52 | G24: 0.54 | H24: 0.5 | I24: 0.7 | J24: 0.7 | K24: 0.55 | L24: 0.6 | M24: 0.75 | N24: 0.65 | O24: 0.55
A25: Stock Change | B25: =B20-B21-B22-B23 -> -0.5 | C25: =C20-C21-C22-C23 -> -0.5 | D25: =D20-D21-D22-D23 -> 0.5 | E25: =E20-E21-E22-E23 -> 0 | F25: =F20-F21-F22-F23 -> -0.8 | G25: =G20-G21-G22-G23 -> -0.4 | H25: =H20-H21-H22-H23 -> -0.4 | I25: =I20-I21-I22-I23 -> -1.22 | ... N25: =N20-N21-N22-N23 -> 2.05
A26: Closing Stock | B26: 8 | C26: =B26+C25 -> 7.5 | D26: =C26+D25 -> 8 | E26: =D26+E25 -> 8 | F26: =E26+F25 -> 7.2 | G26: =F26+G25 -> 6.8 | H26: =G26+H25 -> 6.4 | I26: =H26+I25 -> 5.18 | J26: =I26+J25 -> 6.29 | ... O26: =N26+O25 -> 3.89
A27: Exports % of Production | B27: =(B21+B22)/B20 -> 0.4010989 | C27: =(C21+C22)/C20 -> 0.325 | D27: =(D21+D22)/D20 -> 0.28448276 | E27: =(E21+E22)/E20 -> 0.27067669 | F27: =(F21+F22)/F20 -> 0.4 | G27: =(G21+G22)/G20 -> 0.41428571 | H27: =(H21+H22)/H20 -> 0.435 | I27: =(I21+I22)/I20 -> 0.30454545 | ... O27: =(O21+O22)/O20 -> 0.36
A28: Consumption % of Production | B28: =B23/B20 -> 0.62637363 | C28: =C23/C20 -> 0.70625 | D28: =D23/D20 -> 0.67241379 | E28: =E23/E20 -> 0.72932331 | F28: =F23/F20 -> 0.64210526 | G28: =G23/G20 -> 0.6047619 | H28: =H23/H20 -> 0.585 | I28: =I23/I20 -> 0.75090909 | ... K28: =K23/K20 -> 0.55 | L28: =AVERAGE(B28:K28) -> 0.65884413 | M28: =AVERAGE(C28:L28) -> 0.66209118 | N28: =AVERAGE(D28:M28) -> 0.6576753 | O28: =AVERAGE(E28:N28) -> 0.65620145
A29: Low Grade Arabica Premium
A30: Stock/Use Conillon | B30: =B26/B23 -> 0.70175439 | C30: =C26/C23 -> 0.66371681 | D30: =D26/D23 -> 1.025641 | E30: =E26/E23 -> 0.82474227 | F30: =F26/F23 -> 0.59016393 | G30: =G26/G23 -> 0.53543307 | H30: =H26/H23 -> 0.54700855 | I30: =I26/I23 -> 0.31355932 | ... O30: =O26/O23 -> 0.29469697
A32: Connie Consumption % | C32: =C23/B23-1 -> -0.0087719298 | D32: =D23/C23-1 -> -0.30973451 | E32: =E23/D23-1 -> 0.24358974 | F32: =F23/E23-1 -> 0.25773196 | G32: =G23/F23-1 -> 0.040983607 | H32: =H23/G23-1 -> -0.078740157 | I32: =I23/H23-1 -> 0.41196581 | J32: =J23/I23-1 -> 0.0042372881 | ... O32: =O23/N23-1 -> -0.11705686
A34: All Coffee Production | B34: =B20+B4 -> 50.3 | C34: =C20+C4 -> 51.4 | D34: =D20+D4 -> 57.3 | E34: =E20+E4 -> 50.6 | F34: =F20+F4 -> 67 | G34: =G20+G4 -> 60 | H34: =H20+H4 -> 73 | I34: =I20+I4 -> 58 | ... O34: =O20+O4 -> 66
A35: Overall Consumption Brazil | B35: =B6+B23 -> 20.5 | C35: =C6+C23 -> 21.2 | D35: =D6+D23 -> 22 | E35: =E6+E23 -> 22.7 | F35: =F6+F23 -> 23.4 | G35: =G6+G23 -> 23.4 | H35: 23.5 | I35: 23.6 | J35: 23.7 | K35: 24 | L35: 24 | M35: 23 | N35: 23 | O35: 24
A36: Annual % change consumption | C36: =C35/B35-1 -> 0.034146341 | D36: =D35/C35-1 -> 0.037735849 | E36: =E35/D35-1 -> 0.031818182 | F36: =F35/E35-1 -> 0.030837004 | G36: =G35/F35-1 -> 0 | H36: =H35/G35-1 -> 0.0042735043 | I36: =I35/H35-1 -> 0.0042553191 | J36: =J35/I35-1 -> 0.0042372881 | ... O36: =O35/N35-1 -> 0.043478261
A38: Overall Brazil | B38: 14/15 | C38: 15/16 | D38: 16/17 | E38: 17/18 | F38: 18/19 | G38: 19/20 | H38: 20/21 | I38: 21/22 | J38: 22/23 | K38: 23/24 | L38: 24/25* | M38: 25/26* | N38: 26/27* | O38: 27/28
A39: Production | B39: =B4+B20 -> 50.3 | C39: =C4+C20 -> 51.4 | D39: =D4+D20 -> 57.3 | E39: =E4+E20 -> 50.6 | F39: =F4+F20 -> 67 | G39: =G4+G20 -> 60 | H39: =H4+H20 -> 73 | I39: =I4+I20 -> 58 | ... O39: =O4+O20 -> 66
A40: Green Exports | B40: =B5+B21 -> 33 | C40: =C5+C21 -> 31.8 | D40: =D5+D21 -> 29.3 | E40: =E5+E21 -> 26.9 | F40: =F5+F21 -> 37.3 | G40: =G5+G21 -> 36.2 | H40: =H5+H21 -> 41.6 | I40: =I5+I21 -> 35.6 | ... O40: =O5+O21 -> 37
A41: Soluble Exports | B41: =B22 -> 2.8 | C41: =C22 -> 2.9 | D41: =D22 -> 3 | E41: =E22 -> 2.9 | F41: =F22 -> 4 | G41: =G22 -> 4.2 | H41: =H22 -> 4 | I41: =I22 -> 4.1 | ... O41: =O22 -> 4
A42: Consumption | B42: =B6+B23 -> 20.5 | C42: =C6+C23 -> 21.2 | D42: =D6+D23 -> 22 | E42: =E6+E23 -> 22.7 | F42: =F6+F23 -> 23.4 | G42: =G6+G23 -> 23.4 | H42: =H6+H23 -> 23.4 | I42: =I6+I23 -> 23.6 | ... O42: =O6+O23 -> 24
A43: Stock Change | B43: =B39-B40-B41-B42 -> -6 | C43: =C39-C40-C41-C42 -> -4.5 | D43: =D39-D40-D41-D42 -> 3 | E43: =E39-E40-E41-E42 -> -1.9 | F43: =F39-F40-F41-F42 -> 2.3 | G43: =G39-G40-G41-G42 -> -3.8 | H43: =H39-H40-H41-H42 -> 4 | I43: =I39-I40-I41-I42 -> -5.3 | ... O43: =O39-O40-O41-O42 -> 1
A44: Closing Stock | B44: =B9+B26 -> 23 | C44: =C9+C26 -> 18.5 | D44: =D9+D26 -> 21.5 | E44: =E9+E26 -> 19.6 | F44: =F9+F26 -> 21.9 | G44: =G9+G26 -> 18.1 | H44: =H9+H26 -> 22.1 | I44: =I9+I26 -> 16.8 | ... O44: =O9+O26 -> 16.8
A45: Exports % of Production | B45: =(B40+B41)/B39 -> 0.71172962 | C45: =(C40+C41)/C39 -> 0.67509728 | D45: =(D40+D41)/D39 -> 0.56369983 | E45: =(E40+E41)/E39 -> 0.58893281 | F45: =(F40+F41)/F39 -> 0.61641791 | G45: =(G40+G41)/G39 -> 0.67333333 | H45: =(H40+H41)/H39 -> 0.62465753 | I45: =(I40+I41)/I39 -> 0.68448276 | ... O45: =(O40+O41)/O39 -> 0.62121212
A46: Consumption % of Production | B46: =B42/B39 -> 0.40755467 | C46: =C42/C39 -> 0.41245136 | D46: =D42/D39 -> 0.38394415 | E46: =E42/E39 -> 0.4486166 | F46: =F42/F39 -> 0.34925373 | G46: =G42/G39 -> 0.39 | H46: =H42/H39 -> 0.32054795 | I46: =I42/I39 -> 0.40689655 | ... O46: =O42/O39 -> 0.36363636
A47: Low Grade Arabica Premium
A48: Stock/Use Conillon | B48: =B44/B42 -> 1.1219512 | C48: =C44/C42 -> 0.87264151 | D48: =D44/D42 -> 0.97727273 | E48: =E44/E42 -> 0.86343612 | F48: =F44/F42 -> 0.93589744 | G48: =G44/G42 -> 0.77350427 | H48: =H44/H42 -> 0.94444444 | I48: =I44/I42 -> 0.71186441 | ... O48: =O44/O42 -> 0.7
A50: All Coffee Production | B50: =B39+B23 -> 61.7 | C50: =C39+C23 -> 62.7 | D50: =D39+D23 -> 65.1 | E50: =E39+E23 -> 60.3 | F50: =F39+F23 -> 79.2 | G50: =G39+G23 -> 72.7 | H50: =H39+H23 -> 84.7 | I50: =I39+I23 -> 74.52 | ... O50: =O39+O23 -> 79.2
A51: Overall Consumption Brazil | B51: =B25+B42 -> 20 | C51: =C25+C42 -> 20.7 | D51: =D25+D42 -> 22.5 | E51: =E25+E42 -> 22.7 | F51: =F25+F42 -> 22.6 | G51: =G25+G42 -> 23 | H51: 23.5 | I51: 23.6 | J51: 23.7 | K51: 24 | L51: 24 | M51: 23 | N51: 23 | O51: 24
A52: Annual % change consumption | C52: =C51/B51-1 -> 0.035 | D52: =D51/C51-1 -> 0.086956522 | E52: =E51/D51-1 -> 0.0088888889 | F52: =F51/E51-1 -> -0.0044052863 | G52: =G51/F51-1 -> 0.017699115 | H52: =H51/G51-1 -> 0.02173913 | I52: =I51/H51-1 -> 0.0042553191 | J52: =J51/I51-1 -> 0.0042372881 | ... O52: =O51/N51-1 -> 0.043478261
A57: AgriAcies format
A59: Arabica Jul-Jun | B59: Carry In | C59: Production | D59: Supply | E59: Int Use | F59: Int. % | G59: Exports | H59: Carry Out | I59: STU | K59: Total Jul-Jun | L59: Carry In | M59: Production | N59: Supply | O59: Int Use | P59: Int. % | Q59: Exports | R59: Carry Out | S59: STU
A60: 10/11 | I60: 0.2 | K60: 10/11
A61: 11/12 | I61: 0.22 | K61: 11/12
A62: 12/13 | I62: 0.34 | K62: 12/13
A63: 13/14 | I63: 0.34 | K63: 13/14
A64: 14/15 | I64: 0.26 | K64: 14/15
A65: 15/16 | I65: 0.15 | K65: 15/16
A66: 16/17 | I66: 0.19 | K66: 16/17
A67: 17/18 | I67: 0.2 | K67: 17/18
A68: 18/19 | I68: 0.26 | K68: 18/19
A69: 19/20 | I69: 0.19 | K69: 19/20
A70: 20/21 | I70: 0.31 | K70: 20/21
A71: 21/22 | B71: 14.1 | C71: 31.9 | D71: =C71+B71 -> 46 | E71: 5.1 | G71: 33.4 | H71: =D71-E71-G71 -> 7.5 | I71: =(H71/(G71+E71)) -> 0.19480519 | K71: 21/22 | L71: 12.1 | M71: 54.3 | N71: =M71+L71 -> 66.4 | O71: 21.1 | Q71: 39.7 | R71: =N71-O71-Q71 -> 5.6 | S71: =(R71/(Q71+O71)) -> 0.092105263
A72: 22/23 | B72: =H71 -> 7.5 | C72: 36.6 | D72: =C72+B72 -> 44.1 | E72: 5.3 | G72: 30.8 | H72: =D72-E72-G72 -> 8 | I72: =(H72/(G72+E72)) -> 0.22160665 | K72: 22/23 | L72: =R71 -> 5.6 | M72: 59.1 | N72: =M72+L72 -> 64.7 | O72: 21.3 | Q72: 35.6 | R72: =N72-O72-Q72 -> 7.8 | S72: =(R72/(Q72+O72)) -> 0.1370826
A73: 23/24 | B73: =H72 -> 8 | C73: 44.7 | D73: =C73+B73 -> 52.7 | E73: 8.3 | G73: 35.9 | H73: =D73-E73-G73 -> 8.5 | I73: =(H73/(G73+E73)) -> 0.19230769 | K73: 23/24 | L73: =R72 -> 7.8 | M73: 67.5 | N73: =M73+L73 -> 75.3 | O73: 21.7 | Q73: 47.5 | R73: =N73-O73-Q73 -> 6.1 | S73: =(R73/(Q73+O73)) -> 0.088150289 | W73: AgriAcies
A74: 24/25 | B74: =H73 -> 8.5 | C74: 42.5 | D74: =C74+B74 -> 51 | E74: 8.6 | G74: 35.5 | H74: =D74-E74-G74 -> 6.9 | I74: =(H74/(G74+E74)) -> 0.15646259 | K74: 24/25 | L74: =R73 -> 6.1 | M74: 63.7 | N74: =M74+L74 -> 69.8 | O74: 21.5 | Q74: 46.7 | R74: =N74-O74-Q74 -> 1.6 | S74: =(R74/(Q74+O74)) -> 0.023460411 | W74: Brazil | X74: 2017/18 | Y74: 2018/19 | Z74: 2019/20 | AA74: 2020/21 | AB74: 2021/22 | AC74: 2022/23 | AD74: 2023/24 | AE74: 2024/25 | AF74: 2025/26
A75: 25/26 | B75: =H74 -> 6.9 | C75: 37.9 | D75: =C75+B75 -> 44.8 | E75: 5.3 | G75: 30.5 | H75: =D75-E75-G75 -> 9 | I75: =(H75/(G75+E75)) -> 0.25139665 | K75: 25/26 | L75: =R74 -> 1.6 | M75: 64 | N75: =M75+L75 -> 65.6 | O75: 21.2 | Q75: 41.3 | R75: =N75-O75-Q75 -> 3.1 | S75: =(R75/(Q75+O75)) -> 0.0496 | W75: Production | X75: 35 | Y75: 50 | Z75: 34 | AA75: 54 | AB75: 33 | AC75: 36 | AD75: 41 | AE75: 43.5 | AF75: 34.5
A76: 26/27 | B76: =H75 -> 9 | C76: 50 | D76: =C76+B76 -> 59 | E76: 6.5 | G76: 35 | H76: =D76-E76-G76 -> 17.5 | I76: =(H76/(G76+E76)) -> 0.42168675 | K76: 26/27 | L76: =R75 -> 3.1 | M76: 75 | N76: =M76+L76 -> 78.1 | O76: 21.4 | Q76: 42.2 | R76: =N76-O76-Q76 -> 14.5 | S76: =(R76/(Q76+O76)) -> 0.22798742 | W76: Carry in Stocks | X76: 17 | Y76: 14 | Z76: 22 | AA76: 15 | AB76: 22 | AC76: 16 | AD76: 15 | AE76: 14 | AF76: 12.5
A79: Robusta Apr-Mar | B79: Carry In | C79: Production | D79: Supply | E79: Int Use | F79: Int. % | G79: Exports | H79: Carry Out | I79: STU
A80: 10/11 | I80: 0.17
A81: 11/12 | I81: 0.07
A82: 12/13 | I82: 0.2
A83: 13/14 | I83: 0.2
A84: 14/15 | I84: 0.24
A85: 15/16 | I85: 0.16
A86: 16/17 | I86: 0.23
A87: 17/18 | I87: 0.22
A88: 18/19 | I88: 0.02
A89: 19/20 | I89: 0.21
A90: 20/21 | I90: 0.19
A91: 21/22 | B91: 3.7 | C91: 22.3 | D91: =C91+B91 -> 26 | E91: 15.7 | G91: 6.9 | H91: =D91-E91-G91 -> 3.4 | I91: =(H91/(G91+E91)) -> 0.15044248
A92: 22/23 | B92: =H91 -> 3.4 | C92: 22.6 | D92: =C92+B92 -> 26 | E92: 15.9 | G92: 4.7 | H92: =D92-E92-G92 -> 5.4 | I92: =(H92/(G92+E92)) -> 0.26213592
A93: 23/24 | B93: =H92 -> 5.4 | C93: 22.8 | D93: =C93+B93 -> 28.2 | E93: 14.6 | G93: 9.6 | H93: =D93-E93-G93 -> 4 | I93: =(H93/(G93+E93)) -> 0.16528926
A94: 24/25 | B94: =H93 -> 4 | C94: 21.2 | D94: =C94+B94 -> 25.2 | E94: 11.8 | G94: 12 | H94: =D94-E94-G94 -> 1.4 | I94: =(H94/(G94+E94)) -> 0.058823529
A95: 25/26 | B95: =H94 -> 1.4 | C95: 26.1 | D95: =C95+B95 -> 27.5 | E95: 15.5 | G95: 10 | H95: =D95-E95-G95 -> 2 | I95: =(H95/(G95+E95)) -> 0.078431373
A96: 26/27 | B96: =H95 -> 2 | C96: 25.6 | D96: =C96+B96 -> 27.6 | E96: 15 | G96: 8.7 | H96: =D96-E96-G96 -> 3.9 | I96: =(H96/(G96+E96)) -> 0.16455696

Sheet Coffee Production per region
Q1: Honduras | AJ1: Colombia
B2: Region | C2: % Arabica crop | E2: The following is the estimated timing of the approximate crop availability for export in selected countries:
B3: Sul de Minas | C3: 0.38
B4: Sao Paulo | C4: 0.12 | E4: Arabica
B5: Cerrado | C5: 0.15 | E5: Brazil | F5: 86% in July-December
B6: Zona de Matta | C6: 0.15 | E6: Ethiopia | F6: 75% in January - Jun
B7: Esperito Santo | C7: 0.1 | E7: Honduras: | F7: 60% in January - June
B8: Parana | C8: 0.03 | E8: Kenya | F8: 70% in January - June
B9: Others | C9: 0.07 | E9: Peru | F9: 68% in July - December
B10: Brazil | C10: =SUM(C3:C9) -> 1 | E10: Colombia | F10: Availability is usually (but not always) spread fairly equally throughout the coffee year
E12: Robusta
B13: Region | C13: % Connies | E13: Brazil | F13: 75% January - June
B14: Espirito Santo | C14: 0.7 | E14: Indonesia | F14: 65% July - December
B15: Others | C15: 0.3 | E15: Uganda | F15: 64% January - June
B16: Brazil | C16: =SUM(C14:C15) -> 1 | E16: Viet Nam | F16: 55% January - June
J27: AgriAcies
B28: Region | C28: % Arabica crop | D28: 22/23 not producing | E28: net impact % | F28: Net impact bags | G28: Trend | J28: Arabica | K28: Production | L28: %
B29: Sul de Minas | C29: 0.38 | D29: 0.3 | E29: =D29*C29 -> 0.114 | F29: =D29*G29 -> 5.814 | G29: =C29*$G$36 -> 19.38 | J29: SDM | K29: 20781 | L29: =K29/$K$38 -> 0.40942136
B30: Sao Paulo | C30: 0.12 | D30: 0.2 | E30: =D30*C30 -> 0.024 | F30: =D30*G30 -> 1.224 | G30: =C30*$G$36 -> 6.12 | J30: CER | K30: 7351 | L30: =K30/$K$38 -> 0.14482731
B31: Cerrado | C31: 0.15 | D31: 0.2 | E31: =D31*C31 -> 0.03 | F31: =D31*G31 -> 1.53 | G31: =C31*$G$36 -> 7.65 | J31: ZDM | K31: 10229 | L31: =K31/$K$38 -> 0.20152885
B32: Zona de Mata | C32: 0.15 | D32: 0.1 | E32: =D32*C32 -> 0.015 | F32: =D32*G32 -> 0.765 | G32: =C32*$G$36 -> 7.65 | J32: MOG | K32: 3926 | L32: =K32/$K$38 -> 0.077348937
B33: Esperito Santo | C33: 0.1 | D33: 0 | E33: =D33*C33 -> 0 | F33: =D33*G33 -> 0 | G33: =C33*$G$36 -> 5.1 | J33: WOSP | K33: 2026 | L33: =K33/$K$38 -> 0.039915677
B34: Parana | C34: 0.03 | D34: 0.1 | E34: =D34*C34 -> 0.003 | F34: =D34*G34 -> 0.153 | G34: =C34*$G$36 -> 1.53 | J34: PR | K34: 645 | L34: =K34/$K$38 -> 0.012707607
B35: Others | C35: 0.07 | D35: 0.1 | E35: =D35*C35 -> 0.007 | F35: =D35*G35 -> 0.357 | G35: =C35*$G$36 -> 3.57 | J35: BAA | K35: 1397 | L35: =K35/$K$38 -> 0.027523297
B36: Brazil | C36: =SUM(C29:C35) -> 1 | F36: =SUM(F29:F35) -> 9.843 | G36: 51 | J36: ESA | K36: 3791 | L36: =K36/$K$38 -> 0.074689205
J37: Other A | K37: 611 | L37: =K37/$K$38 -> 0.012037748
J38: Total | K38: =SUM(K29:K37) -> 50757 | L38: =K38/$K$38 -> 1
B39: Region | C39: % Connies | J39: Both basis 26/27
B40: Espirito Santo | C40: 0.7 | J40: AgriAcies
B41: Others | C41: 0.3 | J41: Robusta | K41: Production | L41: %
B42: Brazil | C42: =SUM(C40:C41) -> 1 | J42: ESC | K42: 18130 | L42: =K42/$K$47 -> 0.73522852
J43: BAC | K43: 2796 | L43: =K43/$K$47 -> 0.11338659
J44: RO | K44: 2656 | L44: =K44/$K$47 -> 0.10770915 | AR44: Colombia
J45: ZDM Con | K45: 404 | L45: =K45/$K$47 -> 0.016383471 | AR45: Colombia is a relatively new origin for Melbourne Coffee Merchants, but one that is rapidly becoming one of our most important offerings, due to the quality, versatility, diversity and relative value of the coffees available, and the fact that we’re able to source delicious coffees from there almost all year round.
J46: Other Con | K46: 673 | L46: =K46/$K$47 -> 0.027292267 | AR46: Colombia produces a lot of coffee – over 11 million bags a year – making it the third-largest exporter of coffee in the world, behind Brazil and Vietnam. There are nearly 600,000 coffee producers in the country, and over two-thirds of the production comes from small farms less than three hectares in size. Most farmers have their own ‘micro beneficios’, where they process the coffee themselves before selling it in parchment.
J47: Total | K47: =SUM(K42:K46) -> 24659 | L47: =K47/$K$47 -> 1 | AR47: Coffee is grown across 588 municipalities and 20 growing regions in Colombia, at elevations of 1,200-2,200 metres above sea level. These regions are all very diverse and produce an impressive variety of coffees, thanks to the country’s mountainous topography, wind patterns, and proximity to the equator, which all combine to create a series of tropical microclimates. Most regions have two harvests a year (the main harvest and a “mitica” or fly crop), which is what makes it possible to source coffee from Colombia pretty much all year long.
AR48: History
AR49: Coffee was introduced to Colombia in the late 1700s with the first plantings in the country’s north. Commercial production and export officially started in the 1810s but remained limited. Throughout the 19thcentury, coffee plants spread across the country from farm to farm, but it wasn’t until the 20thcentury that Colombia established itself as a major coffee-growing nation, boosted by the work of the Federación Nacional de Cafeteros de Colombia (FNC).
AR50: Today, Colombia produces exclusively Arabica coffee. The three most common cultivars are Caturra, Typica and Castillo. Most farmers have a mix of these cultivars growing, although there are some who separate production by cultivar. Bourbon, Catimor, Colombia and Tabi cultivars are also grown in Colombia, among others. An outbreak of coffee-leaf rust in the early 2010s resulted in severe setbacks and lower yields, from which Colombia’s production has now begun to recover. This is thanks in part to aggressive treatment and preventative techniques, along with the development and distribution of disease-resistant plants like Castillo.
AR51: Processing
AR52: Traditionally, the majority of coffees from Colombia have been processed using the washed method. During the harvest, cherries are selectively hand picked in up to four passes, with a few weeks between each pass to allow a larger amount of cherries to ripen. Most farmers have a small ‘beneficio’ (wet mill), a manual or electric pulper, and a fermentation tank. Cherries are picked and pulped on the same day, then immediately placed in the fermentation tank for 12-36 days – the length of time being determined by the temperature (higher temperatures will speed up the fermentation process, and lower temperatures will slow it down). Some producers elect to rinse the coffee in parchment intermediately to help control the fermentation process, and others add water to the fermentation tank, which allows them to remove floaters and get a better selection.
AR53: Depending on the region and conditions, the coffee will either be dried in the sun on patios or flat roofs (in warmer, drier conditions) or under cover on Parabolic beds or in polytunnels (at higher altitudes and in colder, wetter conditions). These tunnels are constructed greenhouses – similar in structure to ‘hoop houses’ – that allow airflow through openings on both ends. These structures protect the drying parchment from rain and mist, and also prevent condensation from dripping back onto the drying beans.
AR54: Coffee Growing Regions
AR55: Colombia has 32 departments in total, and 20 of these produce coffee. Melbourne Coffee Merchants works in the following regions in Colombia:
AR56: ANTIOQUIA
AR57: Antioquia is located in central northwestern Colombia.Coffee was introduced to the region in thethe latter part of the 19thcentury. Since then, this mountainous, fertile department has 128,000 hectares of coffee that is produced by a mix of large estates and tiny farms.
AR58: Antioquia only recently became more accessible to coffee buyers, thanks to a transformation of the department led by Sergio Fajardo, who was the governor of the department in 2012-2016. Sergio transformed Antioquia’s capital city, Medellín, from a violent and dangerous place to a world-class tourist destination with a strong economy. Coffee has played a significant role in this this transformation, and as access to many producers has improved, the region has become one of Colombia’s most important and celebrated coffee-producing areas.
AR59: CAUCA
... AR80: We are fortunate to work with Pergamino in Colombia. Pergamino is a progressive, family-owned company, that produce some of their own coffee, and also work very closely with lots of small producers all over Colombia. Pergamino’s pioneering approach has allowed us to connect with some extremely dedicated and quality-focused smallholder producers and to start to build long term and mutually beneficial relationships with them.

Sheet AgriAcies mimic
A1: JUL JUN | B1: Brazil Internal SnD (mn Bags)
A2: Arabica | B2: 14/15 | C2: 15/16 | D2: 16/17 | E2: 17/18 | F2: 18/19 | G2: 19/20 | H2: 20/21 | I2: 21/22 | J2: 22/23 | K2: 23/24 | L2: 24/25* | M2: 25/26* | N2: 26/27* | O2: 27/28 | P2: 28/29
A4: Production | B4: 32.1 | C4: 35.4 | D4: 45.7 | E4: 37.3 | F4: 48 | G4: 39 | H4: ='Coffee SnD ETG'!F5 -> 53 | I4: ='Coffee SnD ETG'!G5 -> 36 | J4: ='Coffee SnD ETG'!H5 -> 37 | K4: ='Coffee SnD ETG'!I5 -> 42 | L4: ='Coffee SnD ETG'!J5 -> 43 | M4: ='Coffee SnD ETG'!K5 -> 37 | N4: ='Coffee SnD ETG'!L5 -> 50 | O4: ='Coffee SnD ETG'!M5 -> 41
A5: Exports | B5: 28.5 | C5: 29.5 | D5: 29 | E5: 26.2 | F5: 33.7 | G5: 31.7 | H5: 36.9 | I5: 33 | J5: 30.8 | K5: 35.9 | L5: 35.3 | M5: 30.5 | N5: 37.5
A6: Consumption | B6: 9.1 | C6: 9.9 | D6: 14.2 | E6: 13 | F6: 11.2 | G6: 10.7 | H6: 11.7 | I6: =I7*I35 -> 7.08 | J6: 5.3 | K6: =K7*K35 -> 8.64 | L6: =L7*L35 -> 9.12 | M6: =M7*M35 -> 4.37 | N6: =N7*N35 -> 6.44
A7: Demand as % of total | B7: =1-B24 -> 0.44 | C7: =1-C24 -> 0.47 | D7: =1-D24 -> 0.65 | E7: =1-E24 -> 0.57 | F7: =1-F24 -> 0.48 | G7: =1-G24 -> 0.46 | H7: =1-H24 -> 0.5 | I7: =1-I24 -> 0.3 | ... N7: =1-N24 -> 0.28
A8: Stock Change | B8: =B4-B5-B6 -> -5.5 | C8: =C4-C5-C6 -> -4 | D8: =D4-D5-D6 -> 2.5 | E8: =E4-E5-E6 -> -1.9 | F8: =F4-F5-F6 -> 3.1 | G8: =G4-G5-G6 -> -3.4 | H8: =H4-H5-H6 -> 4.4 | I8: =I4-I5-I6 -> -4.08 | ... N8: =N4-N5-N6 -> 6.06
A9: Closing Stock | B9: 10 | C9: =B9+C8 -> 6 | D9: =C9+D8 -> 8.5 | E9: =D9+E8 -> 6.6 | F9: =E9+F8 -> 9.7 | G9: =F9+G8 -> 6.3 | H9: =G9+H8 -> 10.7 | I9: =H9+I8 -> 6.62 | J9: =I9+J8 -> 7.52 | ... N9: =M9+N8 -> 11.75
A10: Exports % of Production | B10: =B5/B4 -> 0.88785047 | C10: =C5/C4 -> 0.83333333 | D10: =D5/D4 -> 0.6345733 | E10: =E5/E4 -> 0.70241287 | F10: =F5/F4 -> 0.70208333 | G10: =G5/G4 -> 0.81282051 | H10: =H5/H4 -> 0.69622642 | I10: =I5/I4 -> 0.91666667 | ... N10: =N5/N4 -> 0.75
A11: Consumption % of Production | B11: =B6/B4 -> 0.2834891 | C11: =C6/C4 -> 0.27966102 | D11: =D6/D4 -> 0.3107221 | E11: =E6/E4 -> 0.34852547 | F11: =F6/F4 -> 0.23333333 | G11: =G6/G4 -> 0.27435897 | H11: =H6/H4 -> 0.22075472 | I11: =I6/I4 -> 0.19666667 | ... N11: =N6/N4 -> 0.1288
A12: Stock/Use Arabica | B12: =B9/(B5+B6) -> 0.26595745 | C12: =C9/(C5+C6) -> 0.15228426 | D12: =D9/(D5+D6) -> 0.19675926 | E12: =E9/(E5+E6) -> 0.16836735 | F12: =F9/(F5+F6) -> 0.21603563 | G12: =G9/(G5+G6) -> 0.14858491 | H12: =H9/(H5+H6) -> 0.22016461 | I12: =I9/(I5+I6) -> 0.16516966 | ... N12: =N9/(N5+N6) -> 0.2674101
A13: All Coffee Stocks Brazil | B13: =B9+B26 -> 12 | C13: =C9+C26 -> 7.5 | D13: =D9+D26 -> 10.5 | E13: =E9+E26 -> 8.6 | F13: =F9+F26 -> 12 | G13: =G9+G26 -> 9.4 | H13: =H9+H26 -> 14.4 | I13: =I9+I26 -> 10 | ... N13: =N9+N26 -> 10.2
A15: Arabica Consumption % | C15: =C6/B6-1 -> 0.087912088 | D15: =D6/C6-1 -> 0.43434343 | E15: =E6/D6-1 -> -0.084507042 | F15: =F6/E6-1 -> -0.13846154 | G15: =G6/F6-1 -> -0.044642857 | H15: =H6/G6-1 -> 0.093457944 | I15: =I6/H6-1 -> -0.39487179 | J15: =J6/I6-1 -> -0.25141243 | ... N15: =N6/M6-1 -> 0.47368421
A17: APR MAR | B17: Brazil Internal SnD (mn Bags)
A18: Conillon | B18: 14/15 | C18: 15/16 | D18: 16/17 | E18: 17/18 | F18: 18/19 | G18: 19/20 | H18: 20/21 | I18: 21/22 | J18: 22/23 | K18: 23/24 | L18: 24/25* | M18: 25/26* | N18: 26/27* | O18: 27/28 | P18: 28/29
A20: Production | B20: 18.2 | C20: 16 | D20: ='Coffee SnD ETG'!B21 -> 11.6 | E20: ='Coffee SnD ETG'!C21 -> 13.3 | F20: ='Coffee SnD ETG'!D21 -> 19 | G20: ='Coffee SnD ETG'!E21 -> 21 | H20: ='Coffee SnD ETG'!F21 -> 20 | I20: ='Coffee SnD ETG'!G21 -> 22 | J20: 22.6 | K20: ='Coffee SnD ETG'!I21 -> 24 | L20: 21.5 | M20: ='Coffee SnD ETG'!K21 -> 26 | N20: ='Coffee SnD ETG'!L21 -> 24.6
A21: Green Exports | B21: 4.5 | C21: 2.3 | D21: 0.3 | E21: 0.7 | F21: 3.6 | G21: 4.4 | H21: 4.7 | I21: 2.6 | J21: 1.4 | K21: 8 | L21: 6.5 | M21: 6 | N21: 6
A22: Soluble Exports | B22: 2.8 | C22: 2.9 | D22: 3 | E22: 2.9 | F22: 2.9 | G22: 3.1 | H22: 3 | I22: 3.2 | J22: 2.7 | K22: 2.6 | L22: 3.1 | M22: 3 | N22: 3
A23: Consumption | B23: 11.4 | C23: 11.3 | D23: 7.8 | E23: 9.7 | F23: 12.2 | G23: 12.7 | H23: 11.7 | I23: =I24*I35 -> 16.52 | J23: 15.9 | K23: =K24*K35 -> 15.36 | L23: =L24*L35 -> 14.88 | M23: =M24*M35 -> 18.63 | N23: =N24*N35 -> 16.56
A24: Demand as % of total | B24: 0.56 | C24: 0.53 | D24: 0.35 | E24: 0.43 | F24: 0.52 | G24: 0.54 | H24: 0.5 | I24: 0.7 | J24: 0.78 | K24: 0.64 | L24: 0.62 | M24: 0.81 | N24: 0.72
A25: Stock Change | B25: =B20-B21-B22-B23 -> -0.5 | C25: =C20-C21-C22-C23 -> -0.5 | D25: =D20-D21-D22-D23 -> 0.5 | E25: =E20-E21-E22-E23 -> 0 | F25: =F20-F21-F22-F23 -> 0.3 | G25: =G20-G21-G22-G23 -> 0.8 | H25: =H20-H21-H22-H23 -> 0.6 | I25: =I20-I21-I22-I23 -> -0.32 | ... N25: =N20-N21-N22-N23 -> -0.96
A26: Closing Stock | B26: 2 | C26: =B26+C25 -> 1.5 | D26: =C26+D25 -> 2 | E26: =D26+E25 -> 2 | F26: =E26+F25 -> 2.3 | G26: =F26+G25 -> 3.1 | H26: =G26+H25 -> 3.7 | I26: =H26+I25 -> 3.38 | J26: =I26+J25 -> 5.98 | ... N26: =M26+N25 -> -1.55
A27: Exports % of Production | B27: =(B21+B22)/B20 -> 0.4010989 | C27: =(C21+C22)/C20 -> 0.325 | D27: =(D21+D22)/D20 -> 0.28448276 | E27: =(E21+E22)/E20 -> 0.27067669 | F27: =(F21+F22)/F20 -> 0.34210526 | G27: =(G21+G22)/G20 -> 0.35714286 | H27: =(H21+H22)/H20 -> 0.385 | I27: =(I21+I22)/I20 -> 0.26363636 | ... N27: =(N21+N22)/N20 -> 0.36585366
A28: Consumption % of Production | B28: =B23/B20 -> 0.62637363 | C28: =C23/C20 -> 0.70625 | D28: =D23/D20 -> 0.67241379 | E28: =E23/E20 -> 0.72932331 | F28: =F23/F20 -> 0.64210526 | G28: =G23/G20 -> 0.6047619 | H28: =H23/H20 -> 0.585 | I28: =I23/I20 -> 0.75090909 | ... K28: =K23/K20 -> 0.64 | L28: =AVERAGE(B28:K28) -> 0.66606768 | M28: =AVERAGE(C28:L28) -> 0.67003709 | N28: =AVERAGE(D28:M28) -> 0.6664158
A29: Low Grade Arabica Premium
A30: Stock/Use Conillon | B30: =B26/B23 -> 0.1754386 | C30: =C26/C23 -> 0.13274336 | D30: =D26/D23 -> 0.25641026 | E30: =E26/E23 -> 0.20618557 | F30: =F26/F23 -> 0.18852459 | G30: =G26/G23 -> 0.24409449 | H30: =H26/H23 -> 0.31623932 | I30: =I26/I23 -> 0.20460048 | ... N30: =N26/N23 -> -0.093599034
A32: Connie Consumption % | C32: =C23/B23-1 -> -0.0087719298 | D32: =D23/C23-1 -> -0.30973451 | E32: =E23/D23-1 -> 0.24358974 | F32: =F23/E23-1 -> 0.25773196 | G32: =G23/F23-1 -> 0.040983607 | H32: =H23/G23-1 -> -0.078740157 | I32: =I23/H23-1 -> 0.41196581 | J32: =J23/I23-1 -> -0.037530266 | ... N32: =N23/M23-1 -> -0.11111111
A34: All Coffee Production | B34: =B20+B4 -> 50.3 | C34: =C20+C4 -> 51.4 | D34: =D20+D4 -> 57.3 | E34: =E20+E4 -> 50.6 | F34: =F20+F4 -> 67 | G34: =G20+G4 -> 60 | H34: =H20+H4 -> 73 | I34: =I20+I4 -> 58 | ... N34: =N20+N4 -> 74.6
A35: Overall Consumption Brazil | B35: =B6+B23 -> 20.5 | C35: =C6+C23 -> 21.2 | D35: =D6+D23 -> 22 | E35: =E6+E23 -> 22.7 | F35: =F6+F23 -> 23.4 | G35: =G6+G23 -> 23.4 | H35: 23.5 | I35: 23.6 | J35: 23.7 | K35: 24 | L35: 24 | M35: 23 | N35: 23
A36: Annual % change consumption | C36: =C35/B35-1 -> 0.034146341 | D36: =D35/C35-1 -> 0.037735849 | E36: =E35/D35-1 -> 0.031818182 | F36: =F35/E35-1 -> 0.030837004 | G36: =G35/F35-1 -> 0 | H36: =H35/G35-1 -> 0.0042735043 | I36: =I35/H35-1 -> 0.0042553191 | J36: =J35/I35-1 -> 0.0042372881 | ... N36: =N35/M35-1 -> 0
A38: Overall Brazil | B38: 14/15 | C38: 15/16 | D38: 16/17 | E38: 17/18 | F38: 18/19 | G38: 19/20 | H38: 20/21 | I38: 21/22 | J38: 22/23 | K38: 23/24 | L38: 24/25* | M38: 25/26* | N38: 26/27*
A39: Production | B39: =B4+B20 -> 50.3 | C39: =C4+C20 -> 51.4 | D39: =D4+D20 -> 57.3 | E39: =E4+E20 -> 50.6 | F39: =F4+F20 -> 67 | G39: =G4+G20 -> 60 | H39: =H4+H20 -> 73 | I39: =I4+I20 -> 58 | ... N39: =N4+N20 -> 74.6
A40: Green Exports | B40: =B5+B21 -> 33 | C40: =C5+C21 -> 31.8 | D40: =D5+D21 -> 29.3 | E40: =E5+E21 -> 26.9 | F40: =F5+F21 -> 37.3 | G40: =G5+G21 -> 36.1 | H40: =H5+H21 -> 41.6 | I40: =I5+I21 -> 35.6 | ... N40: =N5+N21 -> 43.5
A41: Soluble Exports | B41: =B22 -> 2.8 | C41: =C22 -> 2.9 | D41: =D22 -> 3 | E41: =E22 -> 2.9 | F41: =F22 -> 2.9 | G41: =G22 -> 3.1 | H41: =H22 -> 3 | I41: =I22 -> 3.2 | ... N41: =N22 -> 3
A42: Consumption | B42: =B6+B23 -> 20.5 | C42: =C6+C23 -> 21.2 | D42: =D6+D23 -> 22 | E42: =E6+E23 -> 22.7 | F42: =F6+F23 -> 23.4 | G42: =G6+G23 -> 23.4 | H42: =H6+H23 -> 23.4 | I42: =I6+I23 -> 23.6 | ... N42: =N6+N23 -> 23
A43: Stock Change | B43: =B39-B40-B41-B42 -> -6 | C43: =C39-C40-C41-C42 -> -4.5 | D43: =D39-D40-D41-D42 -> 3 | E43: =E39-E40-E41-E42 -> -1.9 | F43: =F39-F40-F41-F42 -> 3.4 | G43: =G39-G40-G41-G42 -> -2.6 | H43: =H39-H40-H41-H42 -> 5 | I43: =I39-I40-I41-I42 -> -4.4 | ... N43: =N39-N40-N41-N42 -> 5.1
A44: Closing Stock | B44: =B9+B26 -> 12 | C44: =C9+C26 -> 7.5 | D44: =D9+D26 -> 10.5 | E44: =E9+E26 -> 8.6 | F44: =F9+F26 -> 12 | G44: =G9+G26 -> 9.4 | H44: =H9+H26 -> 14.4 | I44: =I9+I26 -> 10 | ... N44: =N9+N26 -> 10.2
A45: Exports % of Production | B45: =(B40+B41)/B39 -> 0.71172962 | C45: =(C40+C41)/C39 -> 0.67509728 | D45: =(D40+D41)/D39 -> 0.56369983 | E45: =(E40+E41)/E39 -> 0.58893281 | F45: =(F40+F41)/F39 -> 0.6 | G45: =(G40+G41)/G39 -> 0.65333333 | H45: =(H40+H41)/H39 -> 0.6109589 | I45: =(I40+I41)/I39 -> 0.66896552 | ... N45: =(N40+N41)/N39 -> 0.6233244
A46: Consumption % of Production | B46: =B42/B39 -> 0.40755467 | C46: =C42/C39 -> 0.41245136 | D46: =D42/D39 -> 0.38394415 | E46: =E42/E39 -> 0.4486166 | F46: =F42/F39 -> 0.34925373 | G46: =G42/G39 -> 0.39 | H46: =H42/H39 -> 0.32054795 | I46: =I42/I39 -> 0.40689655 | ... N46: =N42/N39 -> 0.30831099
A47: Low Grade Arabica Premium
A48: Stock/Use Conillon | B48: =B44/B42 -> 0.58536585 | C48: =C44/C42 -> 0.35377358 | D48: =D44/D42 -> 0.47727273 | E48: =E44/E42 -> 0.37885463 | F48: =F44/F42 -> 0.51282051 | G48: =G44/G42 -> 0.4017094 | H48: =H44/H42 -> 0.61538462 | I48: =I44/I42 -> 0.42372881 | ... N48: =N44/N42 -> 0.44347826
A50: All Coffee Production | B50: =B39+B23 -> 61.7 | C50: =C39+C23 -> 62.7 | D50: =D39+D23 -> 65.1 | E50: =E39+E23 -> 60.3 | F50: =F39+F23 -> 79.2 | G50: =G39+G23 -> 72.7 | H50: =H39+H23 -> 84.7 | I50: =I39+I23 -> 74.52 | ... N50: =N39+N23 -> 91.16
A51: Overall Consumption Brazil | B51: =B25+B42 -> 20 | C51: =C25+C42 -> 20.7 | D51: =D25+D42 -> 22.5 | E51: =E25+E42 -> 22.7 | F51: =F25+F42 -> 23.7 | G51: =G25+G42 -> 24.2 | H51: 23.5 | I51: 23.6 | J51: 23.7 | K51: 24 | L51: 24 | M51: 23 | N51: 23
A52: Annual % change consumption | C52: =C51/B51-1 -> 0.035 | D52: =D51/C51-1 -> 0.086956522 | E52: =E51/D51-1 -> 0.0088888889 | F52: =F51/E51-1 -> 0.044052863 | G52: =G51/F51-1 -> 0.021097046 | H52: =H51/G51-1 -> -0.02892562 | I52: =I51/H51-1 -> 0.0042553191 | J52: =J51/I51-1 -> 0.0042372881 | ... N52: =N51/M51-1 -> 0
A57: AgriAcies format
A59: Arabica Jul-Jun | B59: Carry In | C59: Production | D59: Supply | E59: Int Use | F59: Int. % | G59: Exports | H59: Carry Out | I59: STU | K59: Total Jul-Jun | L59: Carry In | M59: Production | N59: Supply | O59: Int Use | P59: Int. % | Q59: Exports | R59: Carry Out | S59: STU
A60: 10/11 | I60: 0.2 | K60: 10/11
A61: 11/12 | I61: 0.22 | K61: 11/12
A62: 12/13 | I62: 0.34 | K62: 12/13
A63: 13/14 | I63: 0.34 | K63: 13/14
A64: 14/15 | I64: 0.26 | K64: 14/15
A65: 15/16 | I65: 0.15 | K65: 15/16
A66: 16/17 | I66: 0.19 | K66: 16/17
A67: 17/18 | I67: 0.2 | K67: 17/18
A68: 18/19 | I68: 0.26 | K68: 18/19
A69: 19/20 | I69: 0.19 | K69: 19/20
A70: 20/21 | I70: 0.31 | K70: 20/21
A71: 21/22 | B71: 14.1 | C71: 31.9 | D71: =C71+B71 -> 46 | E71: 5.1 | G71: 33.4 | H71: =D71-E71-G71 -> 7.5 | I71: =(H71/(G71+E71)) -> 0.19480519 | K71: 21/22 | L71: 12.1 | M71: 54.3 | N71: =M71+L71 -> 66.4 | O71: 21.1 | Q71: 39.7 | R71: =N71-O71-Q71 -> 5.6 | S71: =(R71/(Q71+O71)) -> 0.092105263
A72: 22/23 | B72: =H71 -> 7.5 | C72: 36.6 | D72: =C72+B72 -> 44.1 | E72: 5.3 | G72: 30.8 | H72: =D72-E72-G72 -> 8 | I72: =(H72/(G72+E72)) -> 0.22160665 | K72: 22/23 | L72: =R71 -> 5.6 | M72: 59.1 | N72: =M72+L72 -> 64.7 | O72: 21.3 | Q72: 35.6 | R72: =N72-O72-Q72 -> 7.8 | S72: =(R72/(Q72+O72)) -> 0.1370826
A73: 23/24 | B73: =H72 -> 8 | C73: 44.7 | D73: =C73+B73 -> 52.7 | E73: 8.3 | G73: 35.9 | H73: =D73-E73-G73 -> 8.5 | I73: =(H73/(G73+E73)) -> 0.19230769 | K73: 23/24 | L73: =R72 -> 7.8 | M73: 67.5 | N73: =M73+L73 -> 75.3 | O73: 21.7 | Q73: 47.5 | R73: =N73-O73-Q73 -> 6.1 | S73: =(R73/(Q73+O73)) -> 0.088150289
A74: 24/25 | B74: =H73 -> 8.5 | C74: 42.5 | D74: =C74+B74 -> 51 | E74: 8.6 | G74: 35.5 | H74: =D74-E74-G74 -> 6.9 | I74: =(H74/(G74+E74)) -> 0.15646259 | K74: 24/25 | L74: =R73 -> 6.1 | M74: 63.7 | N74: =M74+L74 -> 69.8 | O74: 21.5 | Q74: 46.7 | R74: =N74-O74-Q74 -> 1.6 | S74: =(R74/(Q74+O74)) -> 0.023460411 | W74: Brazil | X74: 2017/18 | Y74: 2018/19 | Z74: 2019/20 | AA74: 2020/21 | AB74: 2021/22 | AC74: 2022/23 | AD74: 2023/24 | AE74: 2024/25 | AF74: 2025/26
A75: 25/26 | B75: =H74 -> 6.9 | C75: 37.9 | D75: =C75+B75 -> 44.8 | E75: 5.3 | G75: 30.5 | H75: =D75-E75-G75 -> 9 | I75: =(H75/(G75+E75)) -> 0.25139665 | K75: 25/26 | L75: =R74 -> 1.6 | M75: 64 | N75: =M75+L75 -> 65.6 | O75: 21.2 | Q75: 41.3 | R75: =N75-O75-Q75 -> 3.1 | S75: =(R75/(Q75+O75)) -> 0.0496 | W75: Production | X75: 35 | Y75: 50 | Z75: 34 | AA75: 54 | AB75: 33 | AC75: 36 | AD75: 41 | AE75: 43.5 | AF75: 34.5
A76: 26/27 | B76: =H75 -> 9 | C76: 50 | D76: =C76+B76 -> 59 | E76: 6.5 | G76: 35 | H76: =D76-E76-G76 -> 17.5 | I76: =(H76/(G76+E76)) -> 0.42168675 | K76: 26/27 | L76: =R75 -> 3.1 | M76: 75 | N76: =M76+L76 -> 78.1 | O76: 21.4 | Q76: 42.2 | R76: =N76-O76-Q76 -> 14.5 | S76: =(R76/(Q76+O76)) -> 0.22798742 | W76: Carry in Stocks | X76: 17 | Y76: 14 | Z76: 22 | AA76: 15 | AB76: 22 | AC76: 16 | AD76: 15 | AE76: 14 | AF76: 12.5
A79: Robusta Apr-Mar | B79: Carry In | C79: Production | D79: Supply | E79: Int Use | F79: Int. % | G79: Exports | H79: Carry Out | I79: STU
A80: 10/11 | I80: 0.17
A81: 11/12 | I81: 0.07
A82: 12/13 | I82: 0.2
A83: 13/14 | I83: 0.2
A84: 14/15 | I84: 0.24
A85: 15/16 | I85: 0.16
A86: 16/17 | I86: 0.23
A87: 17/18 | I87: 0.22
A88: 18/19 | I88: 0.02
A89: 19/20 | I89: 0.21
A90: 20/21 | I90: 0.19
A91: 21/22 | B91: 3.7 | C91: 22.3 | D91: =C91+B91 -> 26 | E91: 15.7 | G91: 6.9 | H91: =D91-E91-G91 -> 3.4 | I91: =(H91/(G91+E91)) -> 0.15044248
A92: 22/23 | B92: =H91 -> 3.4 | C92: 22.6 | D92: =C92+B92 -> 26 | E92: 15.9 | G92: 4.7 | H92: =D92-E92-G92 -> 5.4 | I92: =(H92/(G92+E92)) -> 0.26213592
A93: 23/24 | B93: =H92 -> 5.4 | C93: 22.8 | D93: =C93+B93 -> 28.2 | E93: 14.6 | G93: 9.6 | H93: =D93-E93-G93 -> 4 | I93: =(H93/(G93+E93)) -> 0.16528926
A94: 24/25 | B94: =H93 -> 4 | C94: 21.2 | D94: =C94+B94 -> 25.2 | E94: 11.8 | G94: 12 | H94: =D94-E94-G94 -> 1.4 | I94: =(H94/(G94+E94)) -> 0.058823529
A95: 25/26 | B95: =H94 -> 1.4 | C95: 26.1 | D95: =C95+B95 -> 27.5 | E95: 15.5 | G95: 10 | H95: =D95-E95-G95 -> 2 | I95: =(H95/(G95+E95)) -> 0.078431373
A96: 26/27 | B96: =H95 -> 2 | C96: 25.6 | D96: =C96+B96 -> 27.6 | E96: 15 | G96: 8.7 | H96: =D96-E96-G96 -> 3.9 | I96: =(H96/(G96+E96)) -> 0.16455696
